statly_observe/__init__.py
statly_observe/__main__.py
statly_observe/breadcrumb.py
statly_observe/cli.py
statly_observe/client.py
statly_observe/event.py
statly_observe/scope.py
statly_observe/span.py
statly_observe/telemetry.py
statly_observe/transport.py
statly_observe/integrations/__init__.py
statly_observe/integrations/asgi.py
statly_observe/integrations/django.py
statly_observe/integrations/fastapi.py
statly_observe/integrations/flask.py
statly_observe/integrations/wsgi.py
statly_observe/logger/__init__.py
statly_observe/logger/logger.py
statly_observe/logger/scrubber.py
statly_observe/logger/types.py
statly_observe/logger/destinations/__init__.py
statly_observe/logger/destinations/console.py
statly_observe/logger/destinations/file.py
statly_observe/logger/destinations/observe.py
statly_observe-0.2.0.dist-info/METADATA
statly_observe-0.2.0.dist-info/WHEEL
statly_observe-0.2.0.dist-info/entry_points.txt
statly_observe-0.2.0.dist-info/licenses/LICENSE
statly_observe-0.2.0.dist-info/RECORD
