Metadata-Version: 2.4
Name: statly-observe
Version: 0.2.0
Summary: Error tracking and monitoring SDK for Python applications
Project-URL: Homepage, https://statly.live
Project-URL: Documentation, https://docs.statly.live/sdk/python/installation
Project-URL: Repository, https://github.com/KodyDennon/statly-python
Project-URL: Issues, https://github.com/KodyDennon/statly-python/issues
Author-email: Statly <support@mail.kodydennon.com>
License-Expression: MIT
License-File: LICENSE
Keywords: error-tracking,monitoring,observability,statly
Classifier: Development Status :: 4 - Beta
Classifier: Intended Audience :: Developers
Classifier: License :: OSI Approved :: MIT License
Classifier: Operating System :: OS Independent
Classifier: Programming Language :: Python :: 3
Classifier: Programming Language :: Python :: 3.8
Classifier: Programming Language :: Python :: 3.9
Classifier: Programming Language :: Python :: 3.10
Classifier: Programming Language :: Python :: 3.11
Classifier: Programming Language :: Python :: 3.12
Classifier: Topic :: Software Development :: Libraries :: Python Modules
Classifier: Topic :: System :: Monitoring
Requires-Python: >=3.8
Requires-Dist: requests>=2.25.0
Provides-Extra: celery
Requires-Dist: celery>=5.0.0; extra == 'celery'
Provides-Extra: dev
Requires-Dist: django>=4.0.0; extra == 'dev'
Requires-Dist: fastapi>=0.100.0; extra == 'dev'
Requires-Dist: flask>=2.0.0; extra == 'dev'
Requires-Dist: pytest-asyncio>=0.21.0; extra == 'dev'
Requires-Dist: pytest>=7.0.0; extra == 'dev'
Requires-Dist: responses>=0.23.0; extra == 'dev'
Requires-Dist: starlette>=0.27.0; extra == 'dev'
Provides-Extra: django
Requires-Dist: django>=3.2; extra == 'django'
Provides-Extra: fastapi
Requires-Dist: fastapi>=0.100.0; extra == 'fastapi'
Requires-Dist: starlette>=0.27.0; extra == 'fastapi'
Provides-Extra: flask
Requires-Dist: blinker>=1.4; extra == 'flask'
Requires-Dist: flask>=2.0.0; extra == 'flask'
